{
  "name": "useRaf",
  "description": "Hook that defines the logic for raf callback",
  "examples": [
    "useRaf(() => console.log('callback'));"
  ],
  "usage": "low",
  "apiParameters": [
    {
      "id": 0,
      "parameters": [
        {
          "tag": "param",
          "name": "callback",
          "type": "UseRafCallback",
          "optional": false,
          "description": "The callback to execute",
          "problems": [],
          "source": [
            {
              "number": 8,
              "source": " * @param {UseRafCallback} callback The callback to execute",
              "tokens": {
                "start": " ",
                "delimiter": "*",
                "postDelimiter": " ",
                "tag": "@param",
                "postTag": " ",
                "name": "callback",
                "postName": " ",
                "type": "{UseRafCallback}",
                "postType": " ",
                "description": "The callback to execute",
                "end": "",
                "lineEnd": ""
              }
            }
          ]
        },
        {
          "tag": "param",
          "name": "options.delay",
          "type": "number",
          "optional": true,
          "description": "The delay between each frame in milliseconds",
          "problems": [],
          "source": [
            {
              "number": 9,
              "source": " * @param {number} [options.delay] The delay between each frame in milliseconds",
              "tokens": {
                "start": " ",
                "delimiter": "*",
                "postDelimiter": " ",
                "tag": "@param",
                "postTag": " ",
                "name": "[options.delay]",
                "postName": " ",
                "type": "{number}",
                "postType": " ",
                "description": "The delay between each frame in milliseconds",
                "end": "",
                "lineEnd": ""
              }
            }
          ]
        },
        {
          "tag": "param",
          "name": "options.enabled",
          "type": "boolean",
          "optional": true,
          "description": "Whether the callback should be enabled",
          "problems": [],
          "source": [
            {
              "number": 10,
              "source": " * @param {boolean} [options.enabled=true] Whether the callback should be enabled",
              "tokens": {
                "start": " ",
                "delimiter": "*",
                "postDelimiter": " ",
                "tag": "@param",
                "postTag": " ",
                "name": "[options.enabled=true]",
                "postName": " ",
                "type": "{boolean}",
                "postType": " ",
                "description": "Whether the callback should be enabled",
                "end": "",
                "lineEnd": ""
              }
            }
          ],
          "default": "true"
        }
      ],
      "returns": {
        "tag": "returns",
        "name": "An",
        "type": "UseRafCallbackReturn",
        "optional": false,
        "description": "object of raf callback functions",
        "problems": [],
        "source": [
          {
            "number": 11,
            "source": " * @returns {UseRafCallbackReturn} An object of raf callback functions",
            "tokens": {
              "start": " ",
              "delimiter": "*",
              "postDelimiter": " ",
              "tag": "@returns",
              "postTag": " ",
              "name": "An",
              "postName": " ",
              "type": "{UseRafCallbackReturn}",
              "postType": " ",
              "description": "object of raf callback functions",
              "end": "",
              "lineEnd": ""
            }
          },
          {
            "number": 12,
            "source": " *",
            "tokens": {
              "start": " ",
              "delimiter": "*",
              "postDelimiter": "",
              "tag": "",
              "postTag": "",
              "name": "",
              "postName": "",
              "type": "",
              "postType": "",
              "description": "",
              "end": "",
              "lineEnd": ""
            }
          }
        ]
      }
    }
  ],
  "category": "browser",
  "browserapi": "requestAnimationFrame",
  "hasTests": false,
  "contributors": [
    {
      "name": "debabin",
      "avatar": "https://gravatar.com/avatar/0d80b3fd9c97adcdd11b8c18ecef1054?d=retro"
    }
  ],
  "lastModified": 1754977987000
}
